Metadata-Version: 1.0
Name: nanobrain
Version: 0.1
Summary: Smart troubleshooting assistant for coders <nanobrain.io>
Home-page: https://nanobrain.io
Author: Samandar Ravshanov
Author-email: UNKNOWN
License: UNKNOWN
Platform: UNKNOWN
